{"name": "Euchromiina", "id": 19890888, "predecessors": [{"name": "Arctiini", "id": 643940}], "successors": [{"name": "Aclytia", "id": 2571855}, {"name": "Antichloris", "id": 2571943}, {"name": "Argyroeides", "id": 2572001}, {"name": "Chrostosoma", "id": 2572189}, {"name": "Chrysocale", "id": 2572198}, {"name": "Coreura", "id": 2572235}, {"name": "Correbia", "id": 2572237}, {"name": "Correbidia", "id": 2572239}, {"name": "Cosmosoma", "id": 2572243}, {"name": "Cyanopepla", "id": 2572275}, {"name": "Dasysphinx", "id": 2572305}, {"name": "Delphyre", "id": 2572308}, {"name": "Diptilon", "id": 2572346}, {"name": "Dycladia", "id": 2572368}, {"name": "Epidesma", "id": 2572403}, {"name": "Eucereon", "id": 2572429}, {"name": "Euchromia", "id": 2572439}, {"name": "Gymnelia", "id": 2572554}, {"name": "Homoeocera", "id": 2572618}, {"name": "Horama", "id": 2572623}, {"name": "Hyaleucerea", "id": 2572631}, {"name": "Isanthrene", "id": 2572695}, {"name": "Leucotmemis", "id": 2572765}, {"name": "Loxophlebia", "id": 2572786}, {"name": "Lymire", "id": 2572795}, {"name": "Macrocneme", "id": 2572810}, {"name": "Mesothen", "id": 2572862}, {"name": "Pheia", "id": 2573222}, {"name": "Phoenicoprocta", "id": 2573233}, {"name": "Poliopastea", "id": 2573260}, {"name": "Pseudohyaleucerea", "id": 2573335}, {"name": "Pseudosphex", "id": 2573357}, {"name": "Psilopleura", "id": 2573362}, {"name": "Rhynchopyga", "id": 2573401}, {"name": "Saurita", "id": 2573417}, {"name": "Sphecosoma", "id": 2573491}, {"name": "Syntomeida", "id": 2573537}, {"name": "Uranophora", "id": 2573651}]}