{"name": "Đạo_đức_y_học", "id": 21823, "predecessors": [{"name": "Y_học", "id": 8417}, {"name": "Đạo_đức_sinh_học", "id": 1677145}, {"name": "Hành_vi_con_người", "id": 84233}, {"name": "Công_nghệ_trong_xã_hội", "id": 1677147}], "successors": [{"name": "Kỹ_thuật_di_truyền", "id": 7754}, {"name": "Nghiện", "id": 13792}, {"name": "Sự_riêng_tư", "id": 66538}, {"name": "Tự_sát", "id": 89564}, {"name": "Mại_dâm", "id": 9058}, {"name": "Tội_phạm_tình_dục", "id": 91347}, {"name": "Khiêu_dâm", "id": 370151}, {"name": "Rối_loạn_tâm_thần_và_hành_vi", "id": 1407122}]}