{"name": "Hải_Phòng", "id": 23422, "predecessors": [{"name": "Thành_phố_ven_biển_Việt_Nam", "id": 411429}, {"name": "Lịch_sử_hành_chính_Việt_Nam", "id": 1102462}, {"name": "Sông", "id": 5252}, {"name": "Cảng_Việt_Nam", "id": 54775}, {"name": "Thành_phố_của_Việt_Nam", "id": 19415871}], "successors": [{"name": "Người_Hải_Phòng", "id": 37025}, {"name": "Giao_thông_Hải_Phòng", "id": 258612}, {"name": "Du_lịch_Hải_Phòng", "id": 317179}, {"name": "Văn_hóa_Hải_Phòng", "id": 342009}, {"name": "Sơ_khai_Hải_Phòng", "id": 7665068}, {"name": "Vận_động_viên_Hải_Phòng", "id": 1262466}, {"name": "Cầu_tại_Hải_Phòng", "id": 317594}, {"name": "Đặc_sản_Hải_Phòng", "id": 3336988}, {"name": "VinFast", "id": 14315849}, {"name": "Bí_thư_Thành_ủy_Hải_Phòng", "id": 1288107}, {"name": "Chủ_tịch_Ủy_ban_nhân_dân_thành_phố_Hải_Phòng", "id": 3710921}]}