{"name": "Nhà_soạn_nhạc", "id": 38046, "predecessors": [{"name": "Lý_thuyết_âm_nhạc", "id": 48865}, {"name": "Nghề_nghiệp_trong_công_nghiệp_âm_nhạc", "id": 2413550}, {"name": "Âm_nhạc", "id": 6155}], "successors": [{"name": "Nhà_soạn_nhạc_LGBT", "id": 3247431}, {"name": "Nam_soạn_nhạc", "id": 3392184}, {"name": "Nhà_soạn_nhạc_Đức", "id": 48746}, {"name": "Nhà_soạn_nhạc_Ba_Lan", "id": 48848}, {"name": "Nhà_soạn_nhạc_Áo", "id": 49001}, {"name": "Nhà_soạn_nhạc_Mỹ", "id": 102082}, {"name": "Nhà_soạn_nhạc_Nga", "id": 188997}, {"name": "Nhà_soạn_nhạc_Ý", "id": 198222}, {"name": "Nhà_soạn_nhạc_Việt_Nam", "id": 414424}, {"name": "Nhà_soạn_nhạc_Tây_Ban_Nha", "id": 456802}, {"name": "Nhà_soạn_nhạc_Nhật_Bản", "id": 516097}, {"name": "Nhà_soạn_nhạc_Pháp", "id": 778658}, {"name": "Nhà_soạn_nhạc_Liên_Xô", "id": 2687553}, {"name": "Nữ_ca_sĩ-người_viết_bài_hát", "id": 3209430}, {"name": "Nhà_soạn_nhạc_thế_kỷ_20", "id": 3383968}, {"name": "Nhà_soạn_nhạc_thế_kỷ_21", "id": 3383976}, {"name": "Nhà_soạn_nhạc_opera", "id": 465085}, {"name": "Nhà_soạn_nhạc_kịch_múa", "id": 3420238}, {"name": "Nhà_soạn_nhạc_video_game", "id": 3420239}]}