{"name": "Biểu_tượng_quốc_gia", "id": 39814, "predecessors": [{"name": "Biểu_tượng", "id": 43261}, {"name": "Chủ_nghĩa_dân_tộc", "id": 68567}], "successors": [{"name": "Quốc_ca", "id": 5530}, {"name": "Quốc_kỳ", "id": 13447}, {"name": "Quốc_huy", "id": 39333}, {"name": "Trang_phục_truyền_thống", "id": 786749}, {"name": "Khẩu_hiệu_quốc_gia", "id": 3431747}, {"name": "Món_ăn_quốc_gia", "id": 19755067}, {"name": "Biểu_tượng_quốc_gia_Phần_Lan", "id": 1709269}, {"name": "Biểu_tượng_quốc_gia_Ba_Lan", "id": 19358311}, {"name": "Danh_hiệu_Việt_Nam", "id": 50478}, {"name": "Quốc_bảo_của_Nhật_Bản", "id": 3226142}, {"name": "Bảo_vật_quốc_gia_của_Việt_Nam", "id": 7456392}, {"name": "Quốc_bảo_của_Hàn_Quốc", "id": 15154558}, {"name": "Quốc_bảo_Triều_Tiên", "id": 19557636}, {"name": "Hoàng_thất_Nhật_Bản", "id": 65146}, {"name": "Thiên_hoàng", "id": 454926}]}