{"name": "Người_nhà_Hán", "id": 43440, "predecessors": [{"name": "Nhà_Hán", "id": 27163}, {"name": "Lịch_sử", "id": 3080}], "successors": [{"name": "Nhân_vật_quân_sự_nhà_Hán", "id": 43439}, {"name": "Nhân_vật_chính_trị_nhà_Hán", "id": 43443}, {"name": "Hoàng_đế_nhà_Hán", "id": 320713}, {"name": "Chư_hầu_vương_nhà_Hán", "id": 2443851}, {"name": "Hoàng_hậu_nhà_Hán", "id": 61848}, {"name": "Phi_tần_nhà_Hán", "id": 3154919}, {"name": "Hoàng_thái_hậu_nhà_Hán", "id": 11709300}, {"name": "Nhà_thơ_Trung_Quốc_thời_Hán", "id": 3424961}, {"name": "Nhân_vật_quân_sự_Đông_Hán", "id": 17515718}]}