{"name": "Phật_giáo", "id": 4967, "predecessors": [{"name": "Triết_học", "id": 6845}, {"name": "Tôn_giáo", "id": 4619}], "successors": [{"name": "Tông_phái_Phật_giáo", "id": 11630}, {"name": "Kinh_điển_Phật_giáo", "id": 11631}, {"name": "Triết_lý_Phật_giáo", "id": 11633}, {"name": "Nghệ_thuật_Phật_giáo", "id": 32017}, {"name": "Lịch_sử_Phật_giáo", "id": 65140}, {"name": "Kiến_trúc_Phật_giáo", "id": 324177}, {"name": "Thuật_ngữ_và_khái_niệm_Phật_giáo", "id": 324188}, {"name": "Sơ_khai_Phật_giáo", "id": 1370264}, {"name": "Phật_Thích-ca", "id": 3128594}, {"name": "Nghi_thức_Phật_giáo", "id": 3128782}, {"name": "Địa_điểm_hành_hương_Phật_giáo", "id": 3210367}, {"name": "Thiền_tông", "id": 10902}, {"name": "Chư_thiên_Phật_giáo", "id": 65233}, {"name": "Đại_sư_Phật_giáo", "id": 10903}, {"name": "Danh_vị_Phật_giáo", "id": 2450498}, {"name": "Thiền_sư_Nhật_Bản", "id": 11266}, {"name": "Thiền_sư_Việt_Nam", "id": 11267}, {"name": "Thiền_sư_Ấn_Độ", "id": 11268}, {"name": "Thiền_sư_Trung_Quốc", "id": 11274}, {"name": "Tăng_sĩ_Việt_Nam", "id": 519850}, {"name": "Chùa_Việt_Nam", "id": 18449}, {"name": "Chùa_Nhật_Bản", "id": 25155}, {"name": "Chùa_Thái_Lan", "id": 74648}]}