{"name": "Hồi_giáo", "id": 7818, "predecessors": [{"name": "Văn_hóa_phương_Tây", "id": 27888}, {"name": "Trung_Đông", "id": 20027}], "successors": [{"name": "Lịch_sử_Hồi_giáo", "id": 148246}, {"name": "Sơ_khai_Hồi_giáo", "id": 1685746}, {"name": "Thuật_ngữ_Hồi_giáo", "id": 3231335}, {"name": "Văn_hóa_Hồi_giáo", "id": 3679356}, {"name": "Tranh_cãi_Hồi_giáo", "id": 12485865}, {"name": "Kiến_trúc_Hồi_giáo", "id": 3168835}, {"name": "Jerusalem", "id": 41028}, {"name": "Quốc_gia_thành_viên_Tổ_chức_Hợp_tác_Hồi_giáo", "id": 3713023}, {"name": "Quan_hệ_Hoa_Kỳ-Iran", "id": 14246066}, {"name": "Cộng_đồng_người_Hồi_giáo_Nga", "id": 3430309}, {"name": "Vương_quốc_Sahel", "id": 19554343}, {"name": "Tín_hữu_Hồi_giáo_Ai_Cập", "id": 10195034}, {"name": "Taliban", "id": 472076}, {"name": "Tín_hữu_Hồi_giáo_Indonesia", "id": 10203150}, {"name": "Nhà_Muhammad_Ali", "id": 311535}, {"name": "Người_Hồi", "id": 145180}]}