{"name": "Hokkaidō", "id": 78228, "predecessors": [{"name": "Tỉnh_của_Nhật_Bản", "id": 73546}, {"name": "Đảo_Nhật_Bản", "id": 77710}, {"name": "Tất_cả", "id": 24901}, {"name": "Địa_lý_Nhật_Bản", "id": 53868}, {"name": "Ngôn_ngữ_học", "id": 4054}], "successors": [{"name": "Người_Hokkaidō", "id": 210526}, {"name": "Thành_phố_tỉnh_Hokkaidō", "id": 572620}, {"name": "Thị_trấn_của_Hokkaidō", "id": 572658}, {"name": "Ga_đường_sắt_ở_Sapporo", "id": 19867694}, {"name": "Tàu_điện_ngầm_đô_thị_Sapporo", "id": 19867787}]}